torcharrow/istring_column.py
torcharrow/version.py
torcharrow/pytorch.py
torcharrow/scope.py
torcharrow/idataframe.py
torcharrow/imap_column.py
torcharrow/inumerical_column.py
torcharrow/expression.py
torcharrow/__init__.py
torcharrow/icolumn.py
torcharrow/interop_arrow.py
torcharrow/dtypes.py
torcharrow/ilist_column.py
torcharrow/dispatcher.py
torcharrow/interop.py
torcharrow/trace.py
torcharrow/_interop.py
torcharrow/functional.py
torcharrow/_torcharrow.cpython-39-x86_64-linux-gnu.so
torcharrow/velox_rt/numerical_column_cpu.py
torcharrow/velox_rt/__init__.py
torcharrow/velox_rt/string_column_cpu.py
torcharrow/velox_rt/dataframe_cpu.py
torcharrow/velox_rt/list_column_cpu.py
torcharrow/velox_rt/typing.py
torcharrow/velox_rt/functional.py
torcharrow/velox_rt/map_column_cpu.py
torcharrow/velox_rt/column.py
torcharrow/include/xsimd/xsimd.hpp
torcharrow/include/xsimd/stl/algorithms.hpp
torcharrow/include/xsimd/math/xsimd_rem_pio2.hpp
torcharrow/include/xsimd/types/xsimd_batch_constant.hpp
torcharrow/include/xsimd/types/xsimd_sse4_2_register.hpp
torcharrow/include/xsimd/types/xsimd_sse4_1_register.hpp
torcharrow/include/xsimd/types/xsimd_avx512bw_register.hpp
torcharrow/include/xsimd/types/xsimd_fma4_register.hpp
torcharrow/include/xsimd/types/xsimd_neon_register.hpp
torcharrow/include/xsimd/types/xsimd_neon64_register.hpp
torcharrow/include/xsimd/types/xsimd_avx512f_register.hpp
torcharrow/include/xsimd/types/xsimd_generic_arch.hpp
torcharrow/include/xsimd/types/xsimd_avx_register.hpp
torcharrow/include/xsimd/types/xsimd_api.hpp
torcharrow/include/xsimd/types/xsimd_fma3_sse_register.hpp
torcharrow/include/xsimd/types/xsimd_avx2_register.hpp
torcharrow/include/xsimd/types/xsimd_fma3_avx2_register.hpp
torcharrow/include/xsimd/types/xsimd_sse3_register.hpp
torcharrow/include/xsimd/types/xsimd_utils.hpp
torcharrow/include/xsimd/types/xsimd_all_registers.hpp
torcharrow/include/xsimd/types/xsimd_fma3_avx_register.hpp
torcharrow-0.1.0.dist-info/WHEEL
torcharrow-0.1.0.dist-info/METADATA
torcharrow-0.1.0.dist-info/LICENSE
torcharrow-0.1.0.dist-info/top_level.txt
torcharrow-0.1.0.dist-info/RECORD
